{
  "familyComposition": "独身",
  "personAge": "26",
  "spouseAge": "",
  "mainIncome": "270",
  "spouseMainIncome": "0",
  "sideJobIncome": "0",
  "spouseSideJobIncome": "0",
  "expenseMethod": "簡単",
  "livingCostSimple": "180000",
  "housingCost": "",
  "utilitiesCost": "",
  "communicationCost": "",
  "carCost": "",
  "insuranceCost": "",
  "educationCost": "",
  "otherFixedCost": "0",
  "foodCost": "",
  "dailyNecessitiesCost": "",
  "transportationCost": "",
  "clothingBeautyCost": "",
  "socializingCost": "",
  "hobbyEntertainmentCost": "",
  "otherVariableCost": "0",
  "carFirstReplacementAfterYears": "15",
  "carPrice": "100",
  "carReplacementFrequency": "10",
  "carLoanUsage": "はい",
  "carLoanYears": "7",
  "carLoanType": "銀行ローン",
  "housingType": "賃貸",
  "housePurchasePlan": {
    "age": 35,
    "price": 2500,
    "downPayment": 0,
    "loanYears": 35,
    "interestRate": 0
  },
  "houseRenovationPlans": [
    {
      "age": "50",
      "cost": 150
    }
  ],
  "housePurchaseAge": "",
  "housePurchasePrice": "",
  "headDownPayment": "",
  "housingLoanYears": "",
  "housingLoanInterestRateType": "一般的な想定",
  "housingLoanInterestRate": "",
  "housingLoanStatus": "",
  "loanOriginalAmount": "",
  "loanMonthlyPayment": "",
  "loanRemainingYears": "",
  "loanInterestRate": "",
  "planToMarry": "する",
  "marriageAge": "32",
  "engagementCost": "200",
  "weddingCost": "330",
  "honeymoonCost": "35",
  "newHomeMovingCost": "50",
  "hasChildren": "はい",
  "numberOfChildren": "1",
  "firstBornAge": "37",
  "educationPattern": "公立中心",
  "currentRentLoanPayment": "",
  "otherLargeExpenses": "",
  "parentCurrentAge": "48",
  "parentCareStartAge": "80",
  "parentCareAssumption": "はい",
  "parentCareMonthlyCost": "10",
  "parentCareYears": "5",
  "retirementAge": "65",
  "postRetirementLivingCost": "25",
  "pensionStartAge": "65",
  "pensionAmount": "15",
  "currentSavings": "500",
  "monthlySavings": "50000",
  "hasInvestment": "",
  "investmentStocksCurrent": "",
  "investmentTrustCurrent": "",
  "investmentBondsCurrent": "",
  "investmentIdecoCurrent": "40",
  "investmentCryptoCurrent": "",
  "investmentOtherCurrent": "",
  "monthlyInvestmentAmounts": {
    "investmentStocksMonthly": "0",
    "investmentTrustMonthly": "0",
    "investmentBondsMonthly": "0",
    "investmentIdecoMonthly": "10000",
    "investmentCryptoMonthly": "0",
    "investmentOtherMonthly": "0"
  },
  "investmentStocksAnnualSpot": "0",
  "investmentTrustAnnualSpot": "0",
  "investmentBondsAnnualSpot": "0",
  "investmentIdecoAnnualSpot": "0",
  "investmentCryptoAnnualSpot": "0",
  "investmentOtherAnnualSpot": "0",
  "investmentStocksRate": "6.0",
  "investmentTrustRate": "4.0",
  "investmentBondsRate": "1.0",
  "investmentIdecoRate": "4.0",
  "investmentCryptoRate": "8.0",
  "investmentOtherRate": "0.5",
  "simulationPeriodAge": "90",
  "interestRateScenario": "固定利回り",
  "emergencyFund": "300"
}